simpleais/__init__.py
simpleais/aivdm.json
simpleais/tools.py
simpleais-0.7.3.dist-info/LICENSE
simpleais-0.7.3.dist-info/METADATA
simpleais-0.7.3.dist-info/WHEEL
simpleais-0.7.3.dist-info/entry_points.txt
simpleais-0.7.3.dist-info/top_level.txt
simpleais-0.7.3.dist-info/RECORD
