Metadata-Version: 2.1
Name: simpleais
Version: 0.7.3
Summary: a simple ais parser
Home-page: https://github.com/wpietri/simpleais
Author: William Pietri
Author-email: william-simpleais-0_7@scissor.com
License: Apache 2.0
License-File: LICENSE
Requires-Dist: bitstring
Requires-Dist: testfixtures
Requires-Dist: Click (<8.1.3)
Requires-Dist: numpy
Requires-Dist: python-dateutil
Provides-Extra: dev
Requires-Dist: beautifulsoup4 ; extra == 'dev'
Requires-Dist: nose ; extra == 'dev'
